ecuaciones/__init__.py
ecuaciones/biseccion.py
ecuaciones/cramer.py
ecuaciones/gauss.py
ecuaciones/gauss_jordan.py
ecuaciones/gauss_seidel.py
ecuaciones/jacobi.py
ecuaciones/lu_solve.py
ecuaciones-0.1.6.dist-info/licenses/LICENCE
ecuaciones-0.1.6.dist-info/METADATA
ecuaciones-0.1.6.dist-info/WHEEL
ecuaciones-0.1.6.dist-info/top_level.txt
ecuaciones-0.1.6.dist-info/RECORD
